projectdavid_common/__init__.py
projectdavid_common/utils.py
projectdavid_common/validation.py
projectdavid_common/constants/__init__.py
projectdavid_common/constants/ai_model_map.py
projectdavid_common/constants/assistant_map.py
projectdavid_common/constants/mime_types.py
projectdavid_common/constants/platform.py
projectdavid_common/constants/timeouts.py
projectdavid_common/constants/tools.py
projectdavid_common/schemas/__init__.py
projectdavid_common/schemas/actions_schema.py
projectdavid_common/schemas/api_key_schemas.py
projectdavid_common/schemas/assistants_schema.py
projectdavid_common/schemas/enums.py
projectdavid_common/schemas/files_schema.py
projectdavid_common/schemas/inference_schema.py
projectdavid_common/schemas/messages_schema.py
projectdavid_common/schemas/runs_schema.py
projectdavid_common/schemas/stream_schema.py
projectdavid_common/schemas/threads_schema.py
projectdavid_common/schemas/users_schema.py
projectdavid_common/schemas/vector_search_envelope.py
projectdavid_common/schemas/vectors_schema.py
projectdavid_common/utilities/__init__.py
projectdavid_common/utilities/identifier_service.py
projectdavid_common/utilities/logging_service.py
projectdavid_common-0.21.9.dist-info/METADATA
projectdavid_common-0.21.9.dist-info/WHEEL
projectdavid_common-0.21.9.dist-info/entry_points.txt
projectdavid_common-0.21.9.dist-info/top_level.txt
projectdavid_common-0.21.9.dist-info/RECORD
