Metadata-Version: 2.4
Name: projectdavid_common
Version: 0.21.9
Summary: Common shared custom packages
Author-email: "Francis N." <francis.neequaye@projectdavid.co.uk>
License: MIT
Project-URL: Homepage, https://github.com/frankie336/projectdavid_common
Keywords: shared,internal,utilities,schemas
Requires-Python: >=3.10
Requires-Dist: pydantic
Requires-Dist: typing_extensions
Requires-Dist: httpx
Provides-Extra: dev
Requires-Dist: pytest; extra == "dev"
